Joker/__init__.py
Just_kidding-0.0.2.dist-info/LICENSE
Just_kidding-0.0.2.dist-info/LICENSE.txt
Just_kidding-0.0.2.dist-info/METADATA
Just_kidding-0.0.2.dist-info/WHEEL
Just_kidding-0.0.2.dist-info/top_level.txt
Just_kidding-0.0.2.dist-info/RECORD
