Metadata-Version: 2.1
Name: Just-kidding
Version: 0.0.2
Summary: Just-kidding is a python library for getting random dad jokes and more kinds of jokes
Home-page: https://github.com/Iwertyuiop123653/Joker
Author: Hasty shrimp452
Author-email: hahacoolguystaco@gmail.com
License: MIT
Keywords: Dad jokes
Platform: UNKNOWN
Classifier: Development Status :: 5 - Production/Stable
Classifier: Intended Audience :: Education
Classifier: Operating System :: Microsoft :: Windows :: Windows 10
Classifier: License :: OSI Approved :: MIT License
Classifier: Programming Language :: Python :: 3
License-File: LICENSE
License-File: LICENSE.txt
Requires-Dist: bs4
